<ZT2Strings>
<entityname>
   <!--animal names-->
      <Aranda>Arandaspis</Aranda>
      <Aranda_stt>Arandaspis</Aranda_stt>
      <Aranda_lower>El Arandaspis</Aranda_lower>
      <Aranda_ltt>
         <color r="255" g="248" b="178">
            <b>Arandaspis</b>
         </color>
         <br/>
         Haga click y seleccione un Arandaspis.
      </Aranda_ltt>
</entityname>
<zoopedia_Aranda>
 <entry>Arandaspis</entry>
 <text>
  <cell pady="0" width="1000"/>
  <p/>
  <cell width="260"/>
  <cell width="640" height="320" bgimg="ui/zoopedia/topCellBg.dds">
   <cell width="600" padx="20" pady="20">
   
               <cell width="284">
						 <cell width="96" bgimg="ui/zoopedia/littleBox-128.tga">
						  <img src="entities/units/animals/Aranda/Aranda_Adult_F_icon.dds" sx="0" sy="0" sw="64" sh="64" height="96" width="96"/>
						 </cell>
						 <cell width="16">
						  <img src="ui/zoopedia/icon_male.dds" sx="0" sy="0" sw="64" sh="64" width="16" height="16"/>
						 </cell>
						 <cell width="16">
						  <img src="ui/zoopedia/icon_female.dds" sx="0" sy="0" sw="64" sh="64" width="16" height="16"/>
						 </cell>
						 <cell width="156"/>
                  <br/>   
                  <cell width="32" pady="0">               
                     <img src="ui/zoopedia/extinct.dds" sx="0" sy="0" sw="64" sh="64" width="32" height="32"/>
                  </cell>                 
                  <cell width="224" padx="10" pady="0">
                     <color r="255" g="255" b="255">
                     Estado de conservacion:
                     <br/>
                        <color r="0" g="255" b="0">
                      Extinto
                        </color>
                     </color>                  
                  </cell>
               </cell>   
   
    <cell width="128">
     <color r="255" g="255" b="255">Costa<br/></color>
     <img src="ui/icon_biomes/icon_reef.dds" sx="0" sy="0" sw="128" sh="128" width="96" height="96"/>
    </cell>
    <cell width="128">
     <color r="255" g="255" b="255">Mar del Tetis<br/></color> 
     <img src="ui/icon_maplocations/reef_warm_oceans_worldwide.dds" sx="0" sy="0" sw="256" sh="256" width="96" height="96"/>
    </cell>
    <br/>
    <cell width="284" pady="10">
     <color r="255" g="255" b="255">Clase: <i>(Pteraspida)</i><br/>Orden: Arandaspidiformes <br/>Familia: Arandaspidae <br/>Genero: <i>Arandaspis</i><br/>Especie: <i>A. prionotolepis</i>
     </color>
    </cell>
    <cell width="256" pady="10">
     <img src="UI/zoopedia/biome/reef_zoopedia_biomebrush.dds" sx="0" sy="0" sw="256" sh="85"/>
    </cell>
   </cell>
  </cell>
  <p/>
  <p/>
  <cell width="260"/>
  <cell width="300">
   <cell width="64">
    <img src="ui/zoopedia/fact-icon64.tga" sx="0" sy="0" sw="64" sh="64"/>
   </cell>
   <cell width="176">
    <color r="255" g="255" b="255">
     <font name="arial" size="12" shadowx="2" shadowy="1" shadowa="50">Datos divertidos de Arandaspis</font>
    </color>
   </cell>
   <p/>
   <cell width="280" bgimg="ui/zoopedia/factBG.tga" padx="10">
    <p/>
    <cell width="32" pady="10">
     <img src="ui/zoopedia/fact-bullet.tga" sx="0" sy="0" sw="32" sh="32"/>
    </cell>
    <cell width="202" pady="10">
     <color r="255" g="255" b="255">Arandaspis vivia en el ordovicico.</color>
    </cell>
	<cell width="32" pady="10">
		<img src="ui/zoopedia/fact-bullet.tga" sx="0" sy="0" sw="32" sh="32"/>
	</cell>    
    <cell width="202" pady="10">
     <color r="255" g="255" b="255">Es un pteraspisdo, al igual que Sacabambaspis y Astraspis.</color>
    </cell>
  </cell>
  </cell>
  <cell width="340">
   <color r="255" g="248" b="178">
    Necesitas 1/2 estrellas de fama en el zoo para adoptar un Arandaspis.
   </color>
   <p/>Arandaspis es un genero extinto de peces agnatos (sin mandibulas) que vivieron en el Ordovicico Inferior, hace unos 480-470 millones de años. Es uno de los vertebrados mas antiguos que se conocen. Sus restos fosiles fueron hallados en Alice Springs (Australia) en 1959, pero no se descubrio que era el vertebrado mas antiguo hasta finales de los años 1960. El nombre de Arandaspis proviene de "Aranda", una tribu de aborigenes australianos (hoy conocidos como Arrernte). Arandaspis media unos 15 cm de longitud; tenia un cuerpo hidrodinamico cubierto por filas de escamas protuberantes. La parte anterior del cuerpo, incluyendo la cabeza estaba protegida por gruesas placas, con orificios para los ojos, nostrilo y branquias. Carecia de aletas y su unico metodo de propulsion seria la cola, aplanada horizontalmente; como resultado, debio de nadar de un modo similar a como lo hacen los actuales renacuajos. Aunque no tenia mandibulas, Arandaspis pudo tener algunas placas moviles en la boca que pudo utilizar como labios para succionar las particulas de las que se alimentaba; la posicion baja de la boca sugiere que se alimentaba sobre el fondo del mar.
   </cell>
  <p/>
  <cell width="260"/>
  <cell width="620">
   Informacion de Wikipedia
  <p/>Hecho por Imago
  </cell>
 </text>
</zoopedia_Aranda>
</ZT2Strings>